rustfs-0.1.3.dist-info/METADATA
rustfs-0.1.3.dist-info/WHEEL
rustfs-0.1.3.dist-info/entry_points.txt
rustfs-0.1.3.dist-info/license_files/LICENSE
rustfs/__init__.py
rustfs/core.py
rustfs/rustfs.cpython-311-darwin.so
rustfs-0.1.3.dist-info/RECORD
